7th_day/universal_counter.v
module universal_counter (
    count_out,clk,rst,en,up_down_count,load,load_value
);

input clk,rst,en,up_down_count,load;
input [3:0] load_value;
output reg [3:0]count_out;

always @(posedge clk) begin
    if (rst) begin
        count_out <= 4'b000; //reset the counter to 0.
    end
    else begin
        if (en) begin  //check enable pin.
            if (load) begin
                count_out <= load_value; //load value to count_out.
            end
            else if (up_down_count) begin
                count_out <= count_out +1; // Up counting from load value.
            end
            else begin
                count_out <= count_out -1; // Down counting from load value.
            end
            
        end
    end
    
end
    
endmodule

7th_day/universal_counter_tb.v
`timescale 1ns/1ps
`include "universal_counter.v"

module universal_counter_tb();
reg clk,rst,en,up_down_count,load;
reg [3:0] load_value;
wire [3:0]count_out;

universal_counter dut (
    count_out,clk,rst,en,
    up_down_count,load,load_value
);

always begin
    #5 clk =~clk;
end

initial begin
    $dumpfile ("counter.vcd");
    $dumpvars (1);
    $monitor ("clk=%b\trst=%b\ten=%b\tload=%b\tup_down=%b\tload_value=%b\tcounter_out=%b",
    clk,rst,en,load,up_down_count,load_value,count_out);
end

initial begin
    clk = 0; rst =1;#10;
    rst = 0;
end

initial begin
    en =1; load =1; load_value = 4'd6; #30;
    load =0; up_down_count =1; #40;
    up_down_count =0; #40;

    rst = 1; #10;
    rst =0;
    en =1; load =1; load_value = 4'd8; #30;
    load =0; up_down_count =1; #40;
    up_down_count =0; #40;
    #100;
    $finish;

end
endmodule

7th_day/counter.vcd
$date
	Sun Mar 30 00:48:04 2025
$end
$version
	Icarus Verilog
$end
$timescale
	1ps
$end
$scope module universal_counter_tb $end
$var wire 4 ! count_out [3:0] $end
$var reg 1 " clk $end
$var reg 1 # en $end
$var reg 1 $ load $end
$var reg 4 % load_value [3:0] $end
$var reg 1 & rst $end
$var reg 1 ' up_down_count $end
$upscope $end
$enddefinitions $end
$comment Show the parameter values. $end
$dumpall
$end
#0
$dumpvars
x'
1&
b110 %
1$
1#
0"
bx !
$end
#5000
b0 !
1"
#10000
0"
0&
#15000
b110 !
1"
#20000
0"
#25000
1"
#30000
0"
1'
0$
#35000
b111 !
1"
#40000
0"
#45000
b1000 !
1"
#50000
0"
#55000
b1001 !
1"
#60000
0"
#65000
b1010 !
1"
#70000
0"
0'
#75000
b1001 !
1"
#80000
0"
#85000
b1000 !
1"
#90000
0"
#95000
b111 !
1"
#100000
0"
#105000
b110 !
1"
#110000
0"
1&
#115000
b0 !
1"
#120000
0"
b1000 %
1$
0&
#125000
b1000 !
1"
#130000
0"
#135000
1"
#140000
0"
#145000
1"
#150000
0"
1'
0$
#155000
b1001 !
1"
#160000
0"
#165000
b1010 !
1"
#170000
0"
#175000
b1011 !
1"
#180000
0"
#185000
b1100 !
1"
#190000
0"
0'
#195000
b1011 !
1"
#200000
0"
#205000
b1010 !
1"
#210000
0"
#215000
b1001 !
1"
#220000
0"
#225000
b1000 !
1"
#230000
0"
#235000
b111 !
1"
#240000
0"
#245000
b110 !
1"
#250000
0"
#255000
b101 !
1"
#260000
0"
#265000
b100 !
1"
#270000
0"
#275000
b11 !
1"
#280000
0"
#285000
b10 !
1"
#290000
0"
#295000
b1 !
1"
#300000
0"
#305000
b0 !
1"
#310000
0"
#315000
b1111 !
1"
#320000
0"
#325000
b1110 !
1"
