100_days_of_RTL/1st_day/encoder.v
module encoder (
    input [7:0]in,
    output reg [2:0]out
);

always @(*) begin
    case (in)
        8'b00000001: out = 3'b000;
        8'b00000010: out = 3'b001;
        8'b00000100: out = 3'b010;
        8'b00001000: out = 3'b011;
        8'b00010000: out = 3'b100;
        8'b00100000: out = 3'b101;
        8'b01000000: out = 3'b110;
        8'b10000000: out = 3'b111;
        default: begin
            out= 3'bxxx;
        end
    endcase
end
    
endmodule

100_days_of_RTL/1st_day/encoder_tb.v
`timescale 1ns/1ps
`include "encoder.v"

module encoder_tb();


reg [7:0]in;
wire [2:0]out;

encoder dut(.in(in),.out(out));

initial begin
    $dumpfile("encoder.vcd");
    $dumpvars(1);
    $display("Input            |  Output");
    $monitor("  %b      ->    %b",in,out);
    in = 1;
    repeat (8) begin
        #5 in = in *2 ;
    end
    #5 in = 300;

    $finish;

end








endmodule

1st_day/encoder.vcd
$date
	Tue Mar 25 21:12:34 2025
$end
$version
	Icarus Verilog
$end
$timescale
	1ps
$end
$scope module encoder_tb $end
$var wire 3 ! out [2:0] $end
$var reg 8 " in [7:0] $end
$upscope $end
$enddefinitions $end
$comment Show the parameter values. $end
$dumpall
$end
#0
$dumpvars
b1 "
b0 !
$end
#5000
b1 !
b10 "
#10000
b10 !
b100 "
#15000
b11 !
b1000 "
#20000
b100 !
b10000 "
#25000
b101 !
b100000 "
#30000
b110 !
b1000000 "
#35000
b111 !
b10000000 "
#40000
bx !
b0 "
#45000
b101100 "
