5th_day/alu/alu.v
module alu (
    a,b,sel,carry, result,borrow
);

input [3:0]a,b;
input [2:0] sel;

output reg [3:0] result;
output reg carry,borrow;

always @(*) begin
    case (sel) 
        3'b000: {carry,result}= a+b; // Addition 
        3'b001: {borrow,result}= a-b; //subtraction
        3'b010: result= a&b; //AND
        3'b011: result= a|b; //OR
        3'b100: result= a^b; //XOR
        3'b101: result= a&&b; // Logical AND
        3'b110: result= a||b; // Logical OR
    
        default: 
            result = 4'b0000; //Default ZERO
        
    endcase
end


    
endmodule

5th_day/alu/alu_tb.v
`timescale 1ns/1ps
`include "alu.v"

module alu_tb();

reg [3:0]a,b;
reg [2:0] sel;
wire carry,borrow;
wire [3:0] result;

alu dut(.a(a),.b(b),.sel(sel),.carry(carry),.result(result),.borrow(borrow));

initial begin
    $dumpfile("alu.vcd");
    $dumpvars(0,alu_tb);
    $monitor("a=%b\tb=%b\tsel=%b\tresult=%b\tcarry=%b\tborrow=%b",a,b,sel,result,carry,borrow);
    a=4'b1101;b=4'b0110;sel=3'b000; #5;
    a=4'b1001;b=4'b1110;sel=3'b001; #5;
    a=4'b1100;b=4'b1111;sel=3'b010; #5;
    a=4'b0011;b=4'b0011;sel=3'b011; #5;
    a=4'b1101;b=4'b1110;sel=3'b100; #5;
    a=4'b1111;b=4'b0000;sel=3'b101; #5;
    a=4'b1011;b=4'b1100;sel=3'b110; #5;
    a=4'b1111;b=4'b1111;sel=3'b111; #5;
end

endmodule

5th_day/alu/alu.vcd
$date
	Fri Mar 28 14:30:12 2025
$end
$version
	Icarus Verilog
$end
$timescale
	1ps
$end
$scope module alu_tb $end
$var wire 4 ! result [3:0] $end
$var wire 1 " carry $end
$var wire 1 # borrow $end
$var reg 4 $ a [3:0] $end
$var reg 4 % b [3:0] $end
$var reg 3 & sel [2:0] $end
$scope module dut $end
$var wire 4 ' a [3:0] $end
$var wire 4 ( b [3:0] $end
$var wire 3 ) sel [2:0] $end
$var reg 1 # borrow $end
$var reg 1 " carry $end
$var reg 4 * result [3:0] $end
$upscope $end
$upscope $end
$enddefinitions $end
$comment Show the parameter values. $end
$dumpall
$end
#0
$dumpvars
b11 *
b0 )
b110 (
b1101 '
b0 &
b110 %
b1101 $
x#
1"
b11 !
$end
#5000
1#
b1011 !
b1011 *
b1 &
b1 )
b1110 %
b1110 (
b1001 $
b1001 '
#10000
b1100 !
b1100 *
b10 &
b10 )
b1111 %
b1111 (
b1100 $
b1100 '
#15000
b11 !
b11 *
b11 &
b11 )
b11 %
b11 (
b11 $
b11 '
#20000
b100 &
b100 )
b1110 %
b1110 (
b1101 $
b1101 '
#25000
b0 !
b0 *
b101 &
b101 )
b0 %
b0 (
b1111 $
b1111 '
#30000
b1 !
b1 *
b110 &
b110 )
b1100 %
b1100 (
b1011 $
b1011 '
#35000
b0 !
b0 *
b111 &
b111 )
b1111 %
b1111 (
b1111 $
b1111 '
