2nd_day/decoder.v
module  decoder (
    input [2:0]in,
    output reg [7:0] out
);

always @(*) begin
    case (in)
        3'b000 :out = 8'b00000001; 
        3'b001 :out = 8'b00000010; 
        3'b010 :out = 8'b00000100; 
        3'b011 :out = 8'b00001000; 
        3'b100 :out = 8'b00010000; 
        3'b101 :out = 8'b00100000; 
        3'b110 :out = 8'b01000000; 
        3'b111 :out = 8'b10000000; 
        default: begin
            out = 8'bxxxxxxxx;
        end
    endcase
end
    
endmodule

2nd_day/full_adder/full_adder.v
`include "decoder.v"
module full_adder_using_decoder (
    a,b,cin,sum,carry
);

input a,b,cin;
output sum,carry;

wire [7:0]m;

decoder m1 (.in({a,b,cin}), .out(m));

assign sum = m[1] | m[2] | m[4] | m[7] ;
assign carry = m[3] | m[5] | m[6] | m[7];

    
endmodule

2nd_day/full_adder/full_adder_tb.v
`timescale 1ns/1ps
`include "full_adder.v"

module  full_adder_tb(
);

wire sum, carry;
reg a,b,cin;

full_adder_using_decoder dut(a,b,cin,sum,carry);
initial begin
    $dumpfile("full_adder.vcd");
    $dumpvars(1);
    $monitor ("a=%b\tb=%b\tcin=%b\tsum=%b\tcarry=%b\t",a,b,cin,sum,carry);

        #10 a = 0; b = 0; cin = 0; #10;
        #10 a = 0; b = 0; cin = 1; #10;
        #10 a = 0; b = 1; cin = 0; #10;
        #10 a = 0; b = 1; cin = 1; #10;
        #10 a = 1; b = 0; cin = 0; #10;
        #10 a = 1; b = 0; cin = 1; #10;
        #10 a = 1; b = 1; cin = 0; #10;
        #10 a = 1; b = 1; cin = 1; #10;
        $finish;
end

    
endmodule

2nd_day/full_adder/full_adder.vcd
$date
	Wed Mar 26 01:55:12 2025
$end
$version
	Icarus Verilog
$end
$timescale
	1ps
$end
$scope module full_adder_tb $end
$var wire 1 ! sum $end
$var wire 1 " carry $end
$var reg 1 # a $end
$var reg 1 $ b $end
$var reg 1 % cin $end
$upscope $end
$enddefinitions $end
$comment Show the parameter values. $end
$dumpall
$end
#0
$dumpvars
x%
x$
x#
x"
x!
$end
#10000
0"
0!
0%
0$
0#
#30000
1!
1%
#50000
0%
1$
#70000
1"
0!
1%
#90000
0"
1!
0%
0$
1#
#110000
1"
0!
1%
#130000
0%
1$
#150000
1!
1%
