8th_day/LFSR.v
module LFSR (
    clk,rst,Q
);
    
    input clk,rst;
    output reg [3:0]Q;

    wire D= Q[3]^Q[0];

    always @(posedge clk) begin
        if (rst) begin
            Q[3] <= 1'b1;
            Q[2:0] <= 3'b000;           
        end
        else begin
            Q <= {D,Q[3:1]};
        end      
    end
endmodule

8th_day/LFSR_tb.v
`timescale 1ns/1ps
`include "LFSR.v"

module LFSR_tb;

  reg clk, rst;
  wire [3:0] Q;

  LFSR DUT (
    .clk(clk),
    .rst(rst),
    .Q(Q)
  );

always begin
    #5 clk=~clk;
end

initial begin
    $dumpfile("lfsr.vcd");
    $dumpvars(1);
    $monitor("Time=%0t, rst=%b, clk=%b, Q=%b", $time, rst, clk, Q);
    clk =0;
    rst =1;
    #20;
    rst =0;
    #200;
    $finish;

end

endmodule

8th_day/lfsr.vcd
$date
	Mon Mar 31 13:42:53 2025
$end
$version
	Icarus Verilog
$end
$timescale
	1ps
$end
$scope module LFSR_tb $end
$var wire 4 ! Q [3:0] $end
$var reg 1 " clk $end
$var reg 1 # rst $end
$upscope $end
$enddefinitions $end
$comment Show the parameter values. $end
$dumpall
$end
#0
$dumpvars
1#
0"
bx !
$end
#5000
b1000 !
1"
#10000
0"
#15000
1"
#20000
0"
0#
#25000
b1100 !
1"
#30000
0"
#35000
b1110 !
1"
#40000
0"
#45000
b1111 !
1"
#50000
0"
#55000
b111 !
1"
#60000
0"
#65000
b1011 !
1"
#70000
0"
#75000
b101 !
1"
#80000
0"
#85000
b1010 !
1"
#90000
0"
#95000
b1101 !
1"
#100000
0"
#105000
b110 !
1"
#110000
0"
#115000
b11 !
1"
#120000
0"
#125000
b1001 !
1"
#130000
0"
#135000
b100 !
1"
#140000
0"
#145000
b10 !
1"
#150000
0"
#155000
b1 !
1"
#160000
0"
#165000
b1000 !
1"
#170000
0"
#175000
b1100 !
1"
#180000
0"
#185000
b1110 !
1"
#190000
0"
#195000
b1111 !
1"
#200000
0"
#205000
b111 !
1"
#210000
0"
#215000
b1011 !
1"
