9th_day/ring_reg.v
module ring_reg (
    clk,rst,Q
);

    input clk,rst;
    output reg [3:0]Q;

    always @(posedge clk) begin
        if (rst) begin
            Q<=4'b1000;        
        end
        else begin
            Q<= {Q[0],Q[3:1]};
        end
        
    end

    
    
endmodule

9th_day/ring_reg_tb.v
`timescale 1ns/1ps
`include "ring_reg.v"

module ring_reg_tb();

  reg clk, rst;
  wire [3:0] Q;

ring_reg DUT (
    .clk(clk),
    .rst(rst),
    .Q(Q)
  );

always begin
    #5 clk=~clk;
end

initial begin
    $dumpfile("ring_reg.vcd");
    $dumpvars(1);
    $monitor("Time=%0t, rst=%b, clk=%b, Q=%b", $time, rst, clk, Q);
    clk =0;
    rst =1;
    #20;
    rst =0;
    #100;
    $finish;

end
endmodule

9th_day/ring_reg.vcd
$date
	Mon Mar 31 23:27:34 2025
$end
$version
	Icarus Verilog
$end
$timescale
	1ps
$end
$scope module ring_reg_tb $end
$var wire 4 ! Q [3:0] $end
$var reg 1 " clk $end
$var reg 1 # rst $end
$upscope $end
$enddefinitions $end
$comment Show the parameter values. $end
$dumpall
$end
#0
$dumpvars
1#
0"
bx !
$end
#5000
b1000 !
1"
#10000
0"
#15000
1"
#20000
0"
0#
#25000
b100 !
1"
#30000
0"
#35000
b10 !
1"
#40000
0"
#45000
b1 !
1"
#50000
0"
#55000
b1000 !
1"
#60000
0"
#65000
b100 !
1"
#70000
0"
#75000
b10 !
1"
#80000
0"
#85000
b1 !
1"
#90000
0"
#95000
b1000 !
1"
#100000
0"
#105000
b100 !
1"
#110000
0"
#115000
b10 !
1"
