4th_day/mux2x1.v
module mux2x1 (
    y,a,b,sel
);

input a,b,sel;
output y;

assign y = sel?b:a;


    
endmodule

4th_day/mux4x1/mux4x1.v
`include "/share_folder/verilog/new/100_days_of_RTL/4th_day/mux2x1.v"
//mux3x1 using 2x1 mux

module mux4x1 (
    input [3:0]i,
    input [1:0]sel,
    output y
    
);

wire [1:0]w;

mux2x1 m1 (.a(i[0]),.b(i[1]),.sel(sel[0]),.y(w[0]));
mux2x1 m2 (.a(i[2]),.b(i[3]),.sel(sel[0]),.y(w[1]));

mux2x1 m3 (.a(w[0]),.b(w[1]),.sel(sel[1]),.y(y));
    
endmodule

4th_day/mux4x1/mux4x1_tb.v
`timescale 1ns/1ps
`include "mux4x1.v"

module mux4x1_tb();


reg [3:0]i;
reg [1:0]sel;
wire y;

mux4x1 dut(i,sel,y);

initial begin
    $dumpfile ("mux4x1.vcd");
    $dumpvars(1);
    $monitor("i=%b\tsel=%b\ty=%b\t",i,sel,y);
    i=4'b0000;sel=2'b00;
    repeat (16)begin
            repeat (4) begin
                #5 sel = sel+1;
            end
            sel = 2'b00;
            #5 i = i+1;
        
    end
    $finish;
end

endmodule

4th_day/mux4x1/mux4x1.vcd
$date
	Thu Mar 27 13:01:03 2025
$end
$version
	Icarus Verilog
$end
$timescale
	1ps
$end
$scope module mux4x1_tb $end
$var wire 1 ! y $end
$var reg 4 " i [3:0] $end
$var reg 2 # sel [1:0] $end
$upscope $end
$enddefinitions $end
$comment Show the parameter values. $end
$dumpall
$end
#0
$dumpvars
b0 #
b0 "
0!
$end
#5000
b1 #
#10000
b10 #
#15000
b11 #
#20000
b0 #
#25000
1!
b1 "
#30000
0!
b1 #
#35000
b10 #
#40000
b11 #
#45000
1!
b0 #
#50000
0!
b10 "
#55000
1!
b1 #
#60000
0!
b10 #
#65000
b11 #
#70000
0!
b0 #
#75000
1!
b11 "
#80000
b1 #
#85000
0!
b10 #
#90000
b11 #
#95000
1!
b0 #
#100000
0!
b100 "
#105000
b1 #
#110000
1!
b10 #
#115000
0!
b11 #
#120000
b0 #
#125000
1!
b101 "
#130000
0!
b1 #
#135000
1!
b10 #
#140000
0!
b11 #
#145000
1!
b0 #
#150000
0!
b110 "
#155000
1!
b1 #
#160000
1!
b10 #
#165000
0!
b11 #
#170000
0!
b0 #
#175000
1!
b111 "
#180000
b1 #
#185000
1!
b10 #
#190000
0!
b11 #
#195000
1!
b0 #
#200000
0!
b1000 "
#205000
b1 #
#210000
0!
b10 #
#215000
1!
b11 #
#220000
0!
b0 #
#225000
1!
b1001 "
#230000
0!
b1 #
#235000
0!
b10 #
#240000
1!
b11 #
#245000
1!
b0 #
#250000
0!
b1010 "
#255000
1!
b1 #
#260000
0!
b10 #
#265000
1!
b11 #
#270000
0!
b0 #
#275000
1!
b1011 "
#280000
b1 #
#285000
0!
b10 #
#290000
1!
b11 #
#295000
b0 #
#300000
0!
b1100 "
#305000
b1 #
#310000
1!
b10 #
#315000
b11 #
#320000
0!
b0 #
#325000
1!
b1101 "
#330000
0!
b1 #
#335000
1!
b10 #
#340000
b11 #
#345000
1!
b0 #
#350000
0!
b1110 "
#355000
1!
b1 #
#360000
b10 #
#365000
b11 #
#370000
0!
b0 #
#375000
1!
b1111 "
#380000
b1 #
#385000
b10 #
#390000
b11 #
#395000
b0 #
#400000
0!
b0 "
