3rd_day/ripple_carry_adder.v
module full_adder (
     a,b,cin,sum,cout
);
output sum,cout;
input a,b,cin;

assign sum = a^b^cin;
assign cout = a&b | b&cin |cin&a;
    
endmodule

module ripple_carry_adder ( 
    input [3:0] a,b,
    input cin,
    output cout,
    output [3:0] sum
);

wire [2:0] w;

full_adder m1 (a[0],b[0],cin,sum[0],w[0]);
full_adder m2 (a[1],b[1],w[0],sum[1],w[1]);
full_adder m3 (a[2],b[2],w[1],sum[2],w[2]);
full_adder m4 (a[3],b[3],w[2],sum[3],cout);
    
endmodule

3rd_day/ripple_carry_adder_tb.v
`timescale 1ns/1ps
`include "ripple_carry_adder.v"

module ripple_carry_adder_tb();

reg [3:0]a,b;
reg cin;
wire cout;
wire [3:0]  sum;

ripple_carry_adder dut (.a(a),.b(b),.cin(cin),.cout(cout),.sum(sum));


initial begin
    $dumpfile("ripple_carry_adder.vcd");
    $dumpvars (1);
    $monitor("a=%b\tb=%b\tcin=%b\tsum=%b\tcout=%b\t",a,b,cin,sum,cout);

    a =0;b=0;cin=0;
    #5;
    repeat (15) begin
        #5 a=a+1;
        repeat (15) begin
            #5 b=b+1;
            repeat (2) begin
                #5 cin =~cin;
            end
        end

    end
end



endmodule

3rd_day/ripple_carry_adder.vcd
$date
	Wed Mar 26 16:44:38 2025
$end
$version
	Icarus Verilog
$end
$timescale
	1ps
$end
$scope module ripple_carry_adder_tb $end
$var wire 4 ! sum [3:0] $end
$var wire 1 " cout $end
$var reg 4 # a [3:0] $end
$var reg 4 $ b [3:0] $end
$var reg 1 % cin $end
$upscope $end
$enddefinitions $end
$comment Show the parameter values. $end
$dumpall
$end
#0
$dumpvars
0%
b0 $
b0 #
0"
b0 !
$end
#10000
b1 !
b1 #
#15000
b10 !
b1 $
#20000
b11 !
1%
#25000
b10 !
0%
#30000
b11 !
b10 $
#35000
b100 !
1%
#40000
b11 !
0%
#45000
b100 !
b11 $
#50000
b101 !
1%
#55000
b100 !
0%
#60000
b101 !
b100 $
#65000
b110 !
1%
#70000
b101 !
0%
#75000
b110 !
b101 $
#80000
b111 !
1%
#85000
b110 !
0%
#90000
b111 !
b110 $
#95000
b1000 !
1%
#100000
b111 !
0%
#105000
b1000 !
b111 $
#110000
b1001 !
1%
#115000
b1000 !
0%
#120000
0"
b1001 !
b1000 $
#125000
b1010 !
1%
#130000
b1001 !
0%
#135000
b1010 !
b1001 $
#140000
b1011 !
1%
#145000
b1010 !
0%
#150000
b1011 !
b1010 $
#155000
b1100 !
1%
#160000
b1011 !
0%
#165000
b1100 !
b1011 $
#170000
b1101 !
1%
#175000
b1100 !
0%
#180000
0"
b1101 !
b1100 $
#185000
b1110 !
1%
#190000
b1101 !
0%
#195000
b1110 !
b1101 $
#200000
b1111 !
1%
#205000
b1110 !
0%
#210000
0"
b1111 !
b1110 $
#215000
1"
b0 !
1%
#220000
0"
b1111 !
0%
#225000
1"
b0 !
b1111 $
#230000
b1 !
1%
#235000
b0 !
0%
#240000
b1 !
b10 #
#245000
0"
b10 !
b0 $
#250000
b11 !
1%
#255000
b10 !
0%
#260000
b11 !
b1 $
#265000
b100 !
1%
#270000
b11 !
0%
#275000
b100 !
b10 $
#280000
b101 !
1%
#285000
b100 !
0%
#290000
b101 !
b11 $
#295000
b110 !
1%
#300000
b101 !
0%
#305000
b110 !
b100 $
#310000
b111 !
1%
#315000
b110 !
0%
#320000
b111 !
b101 $
#325000
b1000 !
1%
#330000
b111 !
0%
#335000
b1000 !
b110 $
#340000
b1001 !
1%
#345000
b1000 !
0%
#350000
b1001 !
b111 $
#355000
b1010 !
1%
#360000
b1001 !
0%
#365000
0"
b1010 !
b1000 $
#370000
b1011 !
1%
#375000
b1010 !
0%
#380000
b1011 !
b1001 $
#385000
b1100 !
1%
#390000
b1011 !
0%
#395000
b1100 !
b1010 $
#400000
b1101 !
1%
#405000
b1100 !
0%
#410000
b1101 !
b1011 $
#415000
b1110 !
1%
#420000
b1101 !
0%
#425000
0"
b1110 !
b1100 $
#430000
b1111 !
1%
#435000
b1110 !
0%
#440000
b1111 !
b1101 $
#445000
1"
b0 !
1%
#450000
0"
b1111 !
0%
#455000
1"
b0 !
b1110 $
#460000
b1 !
1%
#465000
b0 !
0%
#470000
b1 !
b11 #
#475000
b10 !
b1111 $
#480000
b11 !
1%
#485000
b10 !
0%
#490000
0"
b11 !
b0 $
#495000
b100 !
1%
#500000
b11 !
0%
#505000
b100 !
b1 $
#510000
b101 !
1%
#515000
b100 !
0%
#520000
b101 !
b10 $
#525000
b110 !
1%
#530000
b101 !
0%
#535000
b110 !
b11 $
#540000
b111 !
1%
#545000
b110 !
0%
#550000
b111 !
b100 $
#555000
b1000 !
1%
#560000
b111 !
0%
#565000
b1000 !
b101 $
#570000
b1001 !
1%
#575000
b1000 !
0%
#580000
b1001 !
b110 $
#585000
b1010 !
1%
#590000
b1001 !
0%
#595000
b1010 !
b111 $
#600000
b1011 !
1%
#605000
b1010 !
0%
#610000
0"
b1011 !
b1000 $
#615000
b1100 !
1%
#620000
b1011 !
0%
#625000
b1100 !
b1001 $
#630000
b1101 !
1%
#635000
b1100 !
0%
#640000
b1101 !
b1010 $
#645000
b1110 !
1%
#650000
b1101 !
0%
#655000
b1110 !
b1011 $
#660000
b1111 !
1%
#665000
b1110 !
0%
#670000
0"
b1111 !
b1100 $
#675000
1"
b0 !
1%
#680000
0"
b1111 !
0%
#685000
1"
b0 !
b1101 $
#690000
b1 !
1%
#695000
b0 !
0%
#700000
b1 !
b100 #
#705000
b10 !
b1110 $
#710000
b11 !
1%
#715000
b10 !
0%
#720000
b11 !
b1111 $
#725000
b100 !
1%
#730000
b11 !
0%
#735000
0"
b100 !
b0 $
#740000
b101 !
1%
#745000
b100 !
0%
#750000
b101 !
b1 $
#755000
b110 !
1%
#760000
b101 !
0%
#765000
b110 !
b10 $
#770000
b111 !
1%
#775000
b110 !
0%
#780000
b111 !
b11 $
#785000
b1000 !
1%
#790000
b111 !
0%
#795000
b1000 !
b100 $
#800000
b1001 !
1%
#805000
b1000 !
0%
#810000
b1001 !
b101 $
#815000
b1010 !
1%
#820000
b1001 !
0%
#825000
b1010 !
b110 $
#830000
b1011 !
1%
#835000
b1010 !
0%
#840000
b1011 !
b111 $
#845000
b1100 !
1%
#850000
b1011 !
0%
#855000
0"
b1100 !
b1000 $
#860000
b1101 !
1%
#865000
b1100 !
0%
#870000
b1101 !
b1001 $
#875000
b1110 !
1%
#880000
b1101 !
0%
#885000
b1110 !
b1010 $
#890000
b1111 !
1%
#895000
b1110 !
0%
#900000
b1111 !
b1011 $
#905000
1"
b0 !
1%
#910000
0"
b1111 !
0%
#915000
1"
b0 !
b1100 $
#920000
b1 !
1%
#925000
b0 !
0%
#930000
b1 !
b101 #
#935000
b10 !
b1101 $
#940000
b11 !
1%
#945000
b10 !
0%
#950000
b11 !
b1110 $
#955000
b100 !
1%
#960000
b11 !
0%
#965000
b100 !
b1111 $
#970000
b101 !
1%
#975000
b100 !
0%
#980000
0"
b101 !
b0 $
#985000
b110 !
1%
#990000
b101 !
0%
#995000
b110 !
b1 $
#1000000
b111 !
1%
#1005000
b110 !
0%
#1010000
b111 !
b10 $
#1015000
b1000 !
1%
#1020000
b111 !
0%
#1025000
b1000 !
b11 $
#1030000
b1001 !
1%
#1035000
b1000 !
0%
#1040000
b1001 !
b100 $
#1045000
b1010 !
1%
#1050000
b1001 !
0%
#1055000
b1010 !
b101 $
#1060000
b1011 !
1%
#1065000
b1010 !
0%
#1070000
b1011 !
b110 $
#1075000
b1100 !
1%
#1080000
b1011 !
0%
#1085000
b1100 !
b111 $
#1090000
b1101 !
1%
#1095000
b1100 !
0%
#1100000
0"
b1101 !
b1000 $
#1105000
b1110 !
1%
#1110000
b1101 !
0%
#1115000
b1110 !
b1001 $
#1120000
b1111 !
1%
#1125000
b1110 !
0%
#1130000
0"
b1111 !
b1010 $
#1135000
1"
b0 !
1%
#1140000
0"
b1111 !
0%
#1145000
1"
b0 !
b1011 $
#1150000
b1 !
1%
#1155000
b0 !
0%
#1160000
b1 !
b110 #
#1165000
b10 !
b1100 $
#1170000
b11 !
1%
#1175000
b10 !
0%
#1180000
b11 !
b1101 $
#1185000
b100 !
1%
#1190000
b11 !
0%
#1195000
b100 !
b1110 $
#1200000
b101 !
1%
#1205000
b100 !
0%
#1210000
b101 !
b1111 $
#1215000
b110 !
1%
#1220000
b101 !
0%
#1225000
0"
b110 !
b0 $
#1230000
b111 !
1%
#1235000
b110 !
0%
#1240000
b111 !
b1 $
#1245000
b1000 !
1%
#1250000
b111 !
0%
#1255000
b1000 !
b10 $
#1260000
b1001 !
1%
#1265000
b1000 !
0%
#1270000
b1001 !
b11 $
#1275000
b1010 !
1%
#1280000
b1001 !
0%
#1285000
b1010 !
b100 $
#1290000
b1011 !
1%
#1295000
b1010 !
0%
#1300000
b1011 !
b101 $
#1305000
b1100 !
1%
#1310000
b1011 !
0%
#1315000
b1100 !
b110 $
#1320000
b1101 !
1%
#1325000
b1100 !
0%
#1330000
b1101 !
b111 $
#1335000
b1110 !
1%
#1340000
b1101 !
0%
#1345000
0"
b1110 !
b1000 $
#1350000
b1111 !
1%
#1355000
b1110 !
0%
#1360000
b1111 !
b1001 $
#1365000
1"
b0 !
1%
#1370000
0"
b1111 !
0%
#1375000
1"
b0 !
b1010 $
#1380000
b1 !
1%
#1385000
b0 !
0%
#1390000
b1 !
b111 #
#1395000
b10 !
b1011 $
#1400000
b11 !
1%
#1405000
b10 !
0%
#1410000
b11 !
b1100 $
#1415000
b100 !
1%
#1420000
b11 !
0%
#1425000
b100 !
b1101 $
#1430000
b101 !
1%
#1435000
b100 !
0%
#1440000
b101 !
b1110 $
#1445000
b110 !
1%
#1450000
b101 !
0%
#1455000
b110 !
b1111 $
#1460000
b111 !
1%
#1465000
b110 !
0%
#1470000
0"
b111 !
b0 $
#1475000
b1000 !
1%
#1480000
b111 !
0%
#1485000
b1000 !
b1 $
#1490000
b1001 !
1%
#1495000
b1000 !
0%
#1500000
b1001 !
b10 $
#1505000
b1010 !
1%
#1510000
b1001 !
0%
#1515000
b1010 !
b11 $
#1520000
b1011 !
1%
#1525000
b1010 !
0%
#1530000
b1011 !
b100 $
#1535000
b1100 !
1%
#1540000
b1011 !
0%
#1545000
b1100 !
b101 $
#1550000
b1101 !
1%
#1555000
b1100 !
0%
#1560000
b1101 !
b110 $
#1565000
b1110 !
1%
#1570000
b1101 !
0%
#1575000
b1110 !
b111 $
#1580000
b1111 !
1%
#1585000
b1110 !
0%
#1590000
0"
b1111 !
b1000 $
#1595000
1"
b0 !
1%
#1600000
0"
b1111 !
0%
#1605000
1"
b0 !
b1001 $
#1610000
b1 !
1%
#1615000
b0 !
0%
#1620000
b1 !
b1000 #
#1625000
b10 !
b1010 $
#1630000
b11 !
1%
#1635000
b10 !
0%
#1640000
b11 !
b1011 $
#1645000
b100 !
1%
#1650000
b11 !
0%
#1655000
b100 !
b1100 $
#1660000
b101 !
1%
#1665000
b100 !
0%
#1670000
b101 !
b1101 $
#1675000
b110 !
1%
#1680000
b101 !
0%
#1685000
b110 !
b1110 $
#1690000
b111 !
1%
#1695000
b110 !
0%
#1700000
b111 !
b1111 $
#1705000
b1000 !
1%
#1710000
b111 !
0%
#1715000
0"
b1000 !
b0 $
#1720000
b1001 !
1%
#1725000
b1000 !
0%
#1730000
b1001 !
b1 $
#1735000
b1010 !
1%
#1740000
b1001 !
0%
#1745000
b1010 !
b10 $
#1750000
b1011 !
1%
#1755000
b1010 !
0%
#1760000
b1011 !
b11 $
#1765000
b1100 !
1%
#1770000
b1011 !
0%
#1775000
b1100 !
b100 $
#1780000
b1101 !
1%
#1785000
b1100 !
0%
#1790000
b1101 !
b101 $
#1795000
b1110 !
1%
#1800000
b1101 !
0%
#1805000
b1110 !
b110 $
#1810000
b1111 !
1%
#1815000
b1110 !
0%
#1820000
b1111 !
b111 $
#1825000
1"
b0 !
1%
#1830000
0"
b1111 !
0%
#1835000
1"
b0 !
b1000 $
#1840000
b1 !
1%
#1845000
b0 !
0%
#1850000
b1 !
b1001 #
#1855000
b10 !
b1001 $
#1860000
b11 !
1%
#1865000
b10 !
0%
#1870000
b11 !
b1010 $
#1875000
b100 !
1%
#1880000
b11 !
0%
#1885000
b100 !
b1011 $
#1890000
b101 !
1%
#1895000
b100 !
0%
#1900000
b101 !
b1100 $
#1905000
b110 !
1%
#1910000
b101 !
0%
#1915000
b110 !
b1101 $
#1920000
b111 !
1%
#1925000
b110 !
0%
#1930000
b111 !
b1110 $
#1935000
b1000 !
1%
#1940000
b111 !
0%
#1945000
b1000 !
b1111 $
#1950000
b1001 !
1%
#1955000
b1000 !
0%
#1960000
0"
b1001 !
b0 $
#1965000
b1010 !
1%
#1970000
b1001 !
0%
#1975000
b1010 !
b1 $
#1980000
b1011 !
1%
#1985000
b1010 !
0%
#1990000
b1011 !
b10 $
#1995000
b1100 !
1%
#2000000
b1011 !
0%
#2005000
b1100 !
b11 $
#2010000
b1101 !
1%
#2015000
b1100 !
0%
#2020000
0"
b1101 !
b100 $
#2025000
b1110 !
1%
#2030000
b1101 !
0%
#2035000
b1110 !
b101 $
#2040000
b1111 !
1%
#2045000
b1110 !
0%
#2050000
0"
b1111 !
b110 $
#2055000
1"
b0 !
1%
#2060000
0"
b1111 !
0%
#2065000
1"
b0 !
b111 $
#2070000
b1 !
1%
#2075000
b0 !
0%
#2080000
b1 !
b1010 #
#2085000
b10 !
b1000 $
#2090000
b11 !
1%
#2095000
b10 !
0%
#2100000
b11 !
b1001 $
#2105000
b100 !
1%
#2110000
b11 !
0%
#2115000
b100 !
b1010 $
#2120000
b101 !
1%
#2125000
b100 !
0%
#2130000
b101 !
b1011 $
#2135000
b110 !
1%
#2140000
b101 !
0%
#2145000
b110 !
b1100 $
#2150000
b111 !
1%
#2155000
b110 !
0%
#2160000
b111 !
b1101 $
#2165000
b1000 !
1%
#2170000
b111 !
0%
#2175000
b1000 !
b1110 $
#2180000
b1001 !
1%
#2185000
b1000 !
0%
#2190000
b1001 !
b1111 $
#2195000
b1010 !
1%
#2200000
b1001 !
0%
#2205000
0"
b1010 !
b0 $
#2210000
b1011 !
1%
#2215000
b1010 !
0%
#2220000
b1011 !
b1 $
#2225000
b1100 !
1%
#2230000
b1011 !
0%
#2235000
b1100 !
b10 $
#2240000
b1101 !
1%
#2245000
b1100 !
0%
#2250000
b1101 !
b11 $
#2255000
b1110 !
1%
#2260000
b1101 !
0%
#2265000
0"
b1110 !
b100 $
#2270000
b1111 !
1%
#2275000
b1110 !
0%
#2280000
b1111 !
b101 $
#2285000
1"
b0 !
1%
#2290000
0"
b1111 !
0%
#2295000
1"
b0 !
b110 $
#2300000
b1 !
1%
#2305000
b0 !
0%
#2310000
b1 !
b1011 #
#2315000
b10 !
b111 $
#2320000
b11 !
1%
#2325000
b10 !
0%
#2330000
b11 !
b1000 $
#2335000
b100 !
1%
#2340000
b11 !
0%
#2345000
b100 !
b1001 $
#2350000
b101 !
1%
#2355000
b100 !
0%
#2360000
b101 !
b1010 $
#2365000
b110 !
1%
#2370000
b101 !
0%
#2375000
b110 !
b1011 $
#2380000
b111 !
1%
#2385000
b110 !
0%
#2390000
b111 !
b1100 $
#2395000
b1000 !
1%
#2400000
b111 !
0%
#2405000
b1000 !
b1101 $
#2410000
b1001 !
1%
#2415000
b1000 !
0%
#2420000
b1001 !
b1110 $
#2425000
b1010 !
1%
#2430000
b1001 !
0%
#2435000
b1010 !
b1111 $
#2440000
b1011 !
1%
#2445000
b1010 !
0%
#2450000
0"
b1011 !
b0 $
#2455000
b1100 !
1%
#2460000
b1011 !
0%
#2465000
b1100 !
b1 $
#2470000
b1101 !
1%
#2475000
b1100 !
0%
#2480000
b1101 !
b10 $
#2485000
b1110 !
1%
#2490000
b1101 !
0%
#2495000
b1110 !
b11 $
#2500000
b1111 !
1%
#2505000
b1110 !
0%
#2510000
0"
b1111 !
b100 $
#2515000
1"
b0 !
1%
#2520000
0"
b1111 !
0%
#2525000
1"
b0 !
b101 $
#2530000
b1 !
1%
#2535000
b0 !
0%
#2540000
b1 !
b1100 #
#2545000
b10 !
b110 $
#2550000
b11 !
1%
#2555000
b10 !
0%
#2560000
b11 !
b111 $
#2565000
b100 !
1%
#2570000
b11 !
0%
#2575000
b100 !
b1000 $
#2580000
b101 !
1%
#2585000
b100 !
0%
#2590000
b101 !
b1001 $
#2595000
b110 !
1%
#2600000
b101 !
0%
#2605000
b110 !
b1010 $
#2610000
b111 !
1%
#2615000
b110 !
0%
#2620000
b111 !
b1011 $
#2625000
b1000 !
1%
#2630000
b111 !
0%
#2635000
b1000 !
b1100 $
#2640000
b1001 !
1%
#2645000
b1000 !
0%
#2650000
b1001 !
b1101 $
#2655000
b1010 !
1%
#2660000
b1001 !
0%
#2665000
b1010 !
b1110 $
#2670000
b1011 !
1%
#2675000
b1010 !
0%
#2680000
b1011 !
b1111 $
#2685000
b1100 !
1%
#2690000
b1011 !
0%
#2695000
0"
b1100 !
b0 $
#2700000
b1101 !
1%
#2705000
b1100 !
0%
#2710000
b1101 !
b1 $
#2715000
b1110 !
1%
#2720000
b1101 !
0%
#2725000
b1110 !
b10 $
#2730000
b1111 !
1%
#2735000
b1110 !
0%
#2740000
b1111 !
b11 $
#2745000
1"
b0 !
1%
#2750000
0"
b1111 !
0%
#2755000
1"
b0 !
b100 $
#2760000
b1 !
1%
#2765000
b0 !
0%
#2770000
b1 !
b1101 #
#2775000
b10 !
b101 $
#2780000
b11 !
1%
#2785000
b10 !
0%
#2790000
b11 !
b110 $
#2795000
b100 !
1%
#2800000
b11 !
0%
#2805000
b100 !
b111 $
#2810000
b101 !
1%
#2815000
b100 !
0%
#2820000
b101 !
b1000 $
#2825000
b110 !
1%
#2830000
b101 !
0%
#2835000
b110 !
b1001 $
#2840000
b111 !
1%
#2845000
b110 !
0%
#2850000
b111 !
b1010 $
#2855000
b1000 !
1%
#2860000
b111 !
0%
#2865000
b1000 !
b1011 $
#2870000
b1001 !
1%
#2875000
b1000 !
0%
#2880000
b1001 !
b1100 $
#2885000
b1010 !
1%
#2890000
b1001 !
0%
#2895000
b1010 !
b1101 $
#2900000
b1011 !
1%
#2905000
b1010 !
0%
#2910000
b1011 !
b1110 $
#2915000
b1100 !
1%
#2920000
b1011 !
0%
#2925000
b1100 !
b1111 $
#2930000
b1101 !
1%
#2935000
b1100 !
0%
#2940000
0"
b1101 !
b0 $
#2945000
b1110 !
1%
#2950000
b1101 !
0%
#2955000
b1110 !
b1 $
#2960000
b1111 !
1%
#2965000
b1110 !
0%
#2970000
0"
b1111 !
b10 $
#2975000
1"
b0 !
1%
#2980000
0"
b1111 !
0%
#2985000
1"
b0 !
b11 $
#2990000
b1 !
1%
#2995000
b0 !
0%
#3000000
b1 !
b1110 #
#3005000
b10 !
b100 $
#3010000
b11 !
1%
#3015000
b10 !
0%
#3020000
b11 !
b101 $
#3025000
b100 !
1%
#3030000
b11 !
0%
#3035000
b100 !
b110 $
#3040000
b101 !
1%
#3045000
b100 !
0%
#3050000
b101 !
b111 $
#3055000
b110 !
1%
#3060000
b101 !
0%
#3065000
b110 !
b1000 $
#3070000
b111 !
1%
#3075000
b110 !
0%
#3080000
b111 !
b1001 $
#3085000
b1000 !
1%
#3090000
b111 !
0%
#3095000
b1000 !
b1010 $
#3100000
b1001 !
1%
#3105000
b1000 !
0%
#3110000
b1001 !
b1011 $
#3115000
b1010 !
1%
#3120000
b1001 !
0%
#3125000
b1010 !
b1100 $
#3130000
b1011 !
1%
#3135000
b1010 !
0%
#3140000
b1011 !
b1101 $
#3145000
b1100 !
1%
#3150000
b1011 !
0%
#3155000
b1100 !
b1110 $
#3160000
b1101 !
1%
#3165000
b1100 !
0%
#3170000
b1101 !
b1111 $
#3175000
b1110 !
1%
#3180000
b1101 !
0%
#3185000
0"
b1110 !
b0 $
#3190000
b1111 !
1%
#3195000
b1110 !
0%
#3200000
b1111 !
b1 $
#3205000
1"
b0 !
1%
#3210000
0"
b1111 !
0%
#3215000
1"
b0 !
b10 $
#3220000
b1 !
1%
#3225000
b0 !
0%
#3230000
b1 !
b1111 #
#3235000
b10 !
b11 $
#3240000
b11 !
1%
#3245000
b10 !
0%
#3250000
b11 !
b100 $
#3255000
b100 !
1%
#3260000
b11 !
0%
#3265000
b100 !
b101 $
#3270000
b101 !
1%
#3275000
b100 !
0%
#3280000
b101 !
b110 $
#3285000
b110 !
1%
#3290000
b101 !
0%
#3295000
b110 !
b111 $
#3300000
b111 !
1%
#3305000
b110 !
0%
#3310000
b111 !
b1000 $
#3315000
b1000 !
1%
#3320000
b111 !
0%
#3325000
b1000 !
b1001 $
#3330000
b1001 !
1%
#3335000
b1000 !
0%
#3340000
b1001 !
b1010 $
#3345000
b1010 !
1%
#3350000
b1001 !
0%
#3355000
b1010 !
b1011 $
#3360000
b1011 !
1%
#3365000
b1010 !
0%
#3370000
b1011 !
b1100 $
#3375000
b1100 !
1%
#3380000
b1011 !
0%
#3385000
b1100 !
b1101 $
#3390000
b1101 !
1%
#3395000
b1100 !
0%
#3400000
b1101 !
b1110 $
#3405000
b1110 !
1%
#3410000
b1101 !
0%
#3415000
b1110 !
b1111 $
#3420000
b1111 !
1%
#3425000
b1110 !
0%
#3430000
0"
b1111 !
b0 $
#3435000
1"
b0 !
1%
#3440000
0"
b1111 !
0%
#3445000
1"
b0 !
b1 $
#3450000
b1 !
1%
#3455000
b0 !
0%
