100_days_of_RTL/1st_day/priority_encoder/priority_encoder.v
module priority_encoder (
    input [7:0]in,
    output reg [2:0]out
);

always @(*) begin
    if (in[7]) begin
        out = 3'b111;
    end
    else if (in[6]) begin
        out = 3'b110;
    end
    else if (in[5]) begin
        out = 3'b101;
    end
    else if (in[4]) begin
        out = 3'b100;
    end
    else if (in[3]) begin
        out = 3'b011;
    end
    else if (in[2]) begin
        out = 3'b010;
    end
    else if (in[1]) begin
        out = 3'b001;
    end
    else  begin
        out = 3'b000;
    end
end



    
endmodule

1st_day/priority_encoder/priority_encoder_tb.v
`timescale 1ns/1ps
`include "/share_folder/verilog/100_days_of_RTL/1st_day/priority_encoder/priority_encoder.v"

module priority_encoder_tb();


reg [7:0]in;
wire [2:0]out;

priority_encoder dut(.in(in),.out(out));

initial begin
    $dumpfile("priority_encoder.vcd");
    $dumpvars(1);
    $display("Input            |  Output");

    $monitor("  %b      ->    %b",in,out);
    in = 0;
    repeat (256) begin
        #5 in = in + 1 ;
    end

    $finish;

end



endmodule

1st_day/priority_encoder/priority_encoder.vcd
$date
	Tue Mar 25 21:17:57 2025
$end
$version
	Icarus Verilog
$end
$timescale
	1ps
$end
$scope module priority_encoder_tb $end
$var wire 3 ! out [2:0] $end
$var reg 8 " in [7:0] $end
$upscope $end
$enddefinitions $end
$comment Show the parameter values. $end
$dumpall
$end
#0
$dumpvars
b0 "
b0 !
$end
#5000
b1 "
#10000
b1 !
b10 "
#15000
b11 "
#20000
b10 !
b100 "
#25000
b101 "
#30000
b110 "
#35000
b111 "
#40000
b11 !
b1000 "
#45000
b1001 "
#50000
b1010 "
#55000
b1011 "
#60000
b1100 "
#65000
b1101 "
#70000
b1110 "
#75000
b1111 "
#80000
b100 !
b10000 "
#85000
b10001 "
#90000
b10010 "
#95000
b10011 "
#100000
b10100 "
#105000
b10101 "
#110000
b10110 "
#115000
b10111 "
#120000
b11000 "
#125000
b11001 "
#130000
b11010 "
#135000
b11011 "
#140000
b11100 "
#145000
b11101 "
#150000
b11110 "
#155000
b11111 "
#160000
b101 !
b100000 "
#165000
b100001 "
#170000
b100010 "
#175000
b100011 "
#180000
b100100 "
#185000
b100101 "
#190000
b100110 "
#195000
b100111 "
#200000
b101000 "
#205000
b101001 "
#210000
b101010 "
#215000
b101011 "
#220000
b101100 "
#225000
b101101 "
#230000
b101110 "
#235000
b101111 "
#240000
b110000 "
#245000
b110001 "
#250000
b110010 "
#255000
b110011 "
#260000
b110100 "
#265000
b110101 "
#270000
b110110 "
#275000
b110111 "
#280000
b111000 "
#285000
b111001 "
#290000
b111010 "
#295000
b111011 "
#300000
b111100 "
#305000
b111101 "
#310000
b111110 "
#315000
b111111 "
#320000
b110 !
b1000000 "
#325000
b1000001 "
#330000
b1000010 "
#335000
b1000011 "
#340000
b1000100 "
#345000
b1000101 "
#350000
b1000110 "
#355000
b1000111 "
#360000
b1001000 "
#365000
b1001001 "
#370000
b1001010 "
#375000
b1001011 "
#380000
b1001100 "
#385000
b1001101 "
#390000
b1001110 "
#395000
b1001111 "
#400000
b1010000 "
#405000
b1010001 "
#410000
b1010010 "
#415000
b1010011 "
#420000
b1010100 "
#425000
b1010101 "
#430000
b1010110 "
#435000
b1010111 "
#440000
b1011000 "
#445000
b1011001 "
#450000
b1011010 "
#455000
b1011011 "
#460000
b1011100 "
#465000
b1011101 "
#470000
b1011110 "
#475000
b1011111 "
#480000
b1100000 "
#485000
b1100001 "
#490000
b1100010 "
#495000
b1100011 "
#500000
b1100100 "
#505000
b1100101 "
#510000
b1100110 "
#515000
b1100111 "
#520000
b1101000 "
#525000
b1101001 "
#530000
b1101010 "
#535000
b1101011 "
#540000
b1101100 "
#545000
b1101101 "
#550000
b1101110 "
#555000
b1101111 "
#560000
b1110000 "
#565000
b1110001 "
#570000
b1110010 "
#575000
b1110011 "
#580000
b1110100 "
#585000
b1110101 "
#590000
b1110110 "
#595000
b1110111 "
#600000
b1111000 "
#605000
b1111001 "
#610000
b1111010 "
#615000
b1111011 "
#620000
b1111100 "
#625000
b1111101 "
#630000
b1111110 "
#635000
b1111111 "
#640000
b111 !
b10000000 "
#645000
b10000001 "
#650000
b10000010 "
#655000
b10000011 "
#660000
b10000100 "
#665000
b10000101 "
#670000
b10000110 "
#675000
b10000111 "
#680000
b10001000 "
#685000
b10001001 "
#690000
b10001010 "
#695000
b10001011 "
#700000
b10001100 "
#705000
b10001101 "
#710000
b10001110 "
#715000
b10001111 "
#720000
b10010000 "
#725000
b10010001 "
#730000
b10010010 "
#735000
b10010011 "
#740000
b10010100 "
#745000
b10010101 "
#750000
b10010110 "
#755000
b10010111 "
#760000
b10011000 "
#765000
b10011001 "
#770000
b10011010 "
#775000
b10011011 "
#780000
b10011100 "
#785000
b10011101 "
#790000
b10011110 "
#795000
b10011111 "
#800000
b10100000 "
#805000
b10100001 "
#810000
b10100010 "
#815000
b10100011 "
#820000
b10100100 "
#825000
b10100101 "
#830000
b10100110 "
#835000
b10100111 "
#840000
b10101000 "
#845000
b10101001 "
#850000
b10101010 "
#855000
b10101011 "
#860000
b10101100 "
#865000
b10101101 "
#870000
b10101110 "
#875000
b10101111 "
#880000
b10110000 "
#885000
b10110001 "
#890000
b10110010 "
#895000
b10110011 "
#900000
b10110100 "
#905000
b10110101 "
#910000
b10110110 "
#915000
b10110111 "
#920000
b10111000 "
#925000
b10111001 "
#930000
b10111010 "
#935000
b10111011 "
#940000
b10111100 "
#945000
b10111101 "
#950000
b10111110 "
#955000
b10111111 "
#960000
b11000000 "
#965000
b11000001 "
#970000
b11000010 "
#975000
b11000011 "
#980000
b11000100 "
#985000
b11000101 "
#990000
b11000110 "
#995000
b11000111 "
#1000000
b11001000 "
#1005000
b11001001 "
#1010000
b11001010 "
#1015000
b11001011 "
#1020000
b11001100 "
#1025000
b11001101 "
#1030000
b11001110 "
#1035000
b11001111 "
#1040000
b11010000 "
#1045000
b11010001 "
#1050000
b11010010 "
#1055000
b11010011 "
#1060000
b11010100 "
#1065000
b11010101 "
#1070000
b11010110 "
#1075000
b11010111 "
#1080000
b11011000 "
#1085000
b11011001 "
#1090000
b11011010 "
#1095000
b11011011 "
#1100000
b11011100 "
#1105000
b11011101 "
#1110000
b11011110 "
#1115000
b11011111 "
#1120000
b11100000 "
#1125000
b11100001 "
#1130000
b11100010 "
#1135000
b11100011 "
#1140000
b11100100 "
#1145000
b11100101 "
#1150000
b11100110 "
#1155000
b11100111 "
#1160000
b11101000 "
#1165000
b11101001 "
#1170000
b11101010 "
#1175000
b11101011 "
#1180000
b11101100 "
#1185000
b11101101 "
#1190000
b11101110 "
#1195000
b11101111 "
#1200000
b11110000 "
#1205000
b11110001 "
#1210000
b11110010 "
#1215000
b11110011 "
#1220000
b11110100 "
#1225000
b11110101 "
#1230000
b11110110 "
#1235000
b11110111 "
#1240000
b11111000 "
#1245000
b11111001 "
#1250000
b11111010 "
#1255000
b11111011 "
#1260000
b11111100 "
#1265000
b11111101 "
#1270000
b11111110 "
#1275000
b11111111 "
#1280000
b0 !
b0 "
