4th_day/mux2x1.v
module mux2x1 (
    y,a,b,sel
);

input a,b,sel;
output y;

assign y = sel?b:a;


    
endmodule

4th_day/mux4x1/mux4x1.v
`include "/share_folder/verilog/new/100_days_of_RTL/4th_day/mux2x1.v"
//mux3x1 using 2x1 mux

module mux4x1 (
    input [3:0]i,
    input [1:0]sel,
    output y
    
);

wire [1:0]w;

mux2x1 m1 (.a(i[0]),.b(i[1]),.sel(sel[0]),.y(w[0]));
mux2x1 m2 (.a(i[2]),.b(i[3]),.sel(sel[0]),.y(w[1]));

mux2x1 m3 (.a(w[0]),.b(w[1]),.sel(sel[1]),.y(y));
    
endmodule

4th_day/mux8x1/mux8x1.v
`include "/share_folder/verilog/new/100_days_of_RTL/4th_day/mux4x1/mux4x1.v"
// making 8x1 mux by using 2 4x1 and 1 2x1 muxes


module mux8x1 (
    I,SEL,Y
);

input [7:0]I;
input [2:0]SEL;
output Y;
wire [1:0]W;


mux4x1 M1 (.i(I[3:0]),.sel(SEL[1:0]),.y(W[0]));
mux4x1 M2 (.i(I[7:4]),.sel(SEL[1:0]),.y(W[1]));


mux2x1 M3 (.a(W[0]),.b(W[1]),.sel(SEL[2]),.y(Y) );


  
endmodule

4th_day/mux8x1/mux8x1_tb.v
`timescale 1ns/1ps
`include "mux8x1.v"

module mux8x1_tb();

reg [7:0]I;
reg [2:0]SEL;
wire Y;

mux8x1 dut(I,SEL,Y);
initial begin
    $dumpfile ("mux4x1.vcd");
    $dumpvars(1);
    $monitor("I=%b\tSEL=%b\tY=%b\t",I,SEL,Y);
    I= 8'b00000001;SEL=3'b000;
    repeat (256)begin
            repeat (8) begin
                #5 SEL = SEL+1;
            end
            SEL =3'b000;
            #5 I = I+1;
        
    end
    $finish;
end


endmodule

4th_day/mux8x1/mux4x1.vcd
$date
	Thu Mar 27 13:32:25 2025
$end
$version
	Icarus Verilog
$end
$timescale
	1ps
$end
$scope module mux8x1_tb $end
$var wire 1 ! Y $end
$var reg 8 " I [7:0] $end
$var reg 3 # SEL [2:0] $end
$upscope $end
$enddefinitions $end
$comment Show the parameter values. $end
$dumpall
$end
#0
$dumpvars
b0 #
b1 "
1!
$end
#5000
0!
b1 #
#10000
b10 #
#15000
b11 #
#20000
b100 #
#25000
b101 #
#30000
b110 #
#35000
b111 #
#40000
1!
b0 #
#45000
0!
b10 "
#50000
1!
b1 #
#55000
0!
b10 #
#60000
b11 #
#65000
b100 #
#70000
b101 #
#75000
b110 #
#80000
b111 #
#85000
0!
b0 #
#90000
1!
b11 "
#95000
b1 #
#100000
0!
b10 #
#105000
b11 #
#110000
b100 #
#115000
b101 #
#120000
b110 #
#125000
b111 #
#130000
1!
b0 #
#135000
0!
b100 "
#140000
b1 #
#145000
1!
b10 #
#150000
0!
b11 #
#155000
b100 #
#160000
b101 #
#165000
b110 #
#170000
b111 #
#175000
b0 #
#180000
1!
b101 "
#185000
0!
b1 #
#190000
1!
b10 #
#195000
0!
b11 #
#200000
b100 #
#205000
b101 #
#210000
b110 #
#215000
b111 #
#220000
1!
b0 #
#225000
0!
b110 "
#230000
1!
b1 #
#235000
1!
b10 #
#240000
0!
b11 #
#245000
b100 #
#250000
b101 #
#255000
b110 #
#260000
b111 #
#265000
0!
b0 #
#270000
1!
b111 "
#275000
b1 #
#280000
1!
b10 #
#285000
0!
b11 #
#290000
b100 #
#295000
b101 #
#300000
b110 #
#305000
b111 #
#310000
1!
b0 #
#315000
0!
b1000 "
#320000
b1 #
#325000
0!
b10 #
#330000
1!
b11 #
#335000
0!
b100 #
#340000
b101 #
#345000
b110 #
#350000
b111 #
#355000
0!
b0 #
#360000
1!
b1001 "
#365000
0!
b1 #
#370000
0!
b10 #
#375000
1!
b11 #
#380000
0!
b100 #
#385000
b101 #
#390000
b110 #
#395000
b111 #
#400000
1!
b0 #
#405000
0!
b1010 "
#410000
1!
b1 #
#415000
0!
b10 #
#420000
1!
b11 #
#425000
0!
b100 #
#430000
b101 #
#435000
b110 #
#440000
b111 #
#445000
0!
b0 #
#450000
1!
b1011 "
#455000
b1 #
#460000
0!
b10 #
#465000
1!
b11 #
#470000
0!
b100 #
#475000
b101 #
#480000
b110 #
#485000
b111 #
#490000
1!
b0 #
#495000
0!
b1100 "
#500000
b1 #
#505000
1!
b10 #
#510000
b11 #
#515000
0!
b100 #
#520000
b101 #
#525000
b110 #
#530000
b111 #
#535000
0!
b0 #
#540000
1!
b1101 "
#545000
0!
b1 #
#550000
1!
b10 #
#555000
b11 #
#560000
0!
b100 #
#565000
b101 #
#570000
b110 #
#575000
b111 #
#580000
1!
b0 #
#585000
0!
b1110 "
#590000
1!
b1 #
#595000
b10 #
#600000
b11 #
#605000
0!
b100 #
#610000
b101 #
#615000
b110 #
#620000
b111 #
#625000
0!
b0 #
#630000
1!
b1111 "
#635000
b1 #
#640000
b10 #
#645000
b11 #
#650000
0!
b100 #
#655000
b101 #
#660000
b110 #
#665000
b111 #
#670000
1!
b0 #
#675000
0!
b10000 "
#680000
b1 #
#685000
b10 #
#690000
b11 #
#695000
1!
b100 #
#700000
0!
b101 #
#705000
b110 #
#710000
b111 #
#715000
b0 #
#720000
1!
b10001 "
#725000
0!
b1 #
#730000
b10 #
#735000
b11 #
#740000
1!
b100 #
#745000
0!
b101 #
#750000
b110 #
#755000
b111 #
#760000
1!
b0 #
#765000
0!
b10010 "
#770000
1!
b1 #
#775000
0!
b10 #
#780000
b11 #
#785000
1!
b100 #
#790000
0!
b101 #
#795000
b110 #
#800000
b111 #
#805000
0!
b0 #
#810000
1!
b10011 "
#815000
b1 #
#820000
0!
b10 #
#825000
b11 #
#830000
1!
b100 #
#835000
0!
b101 #
#840000
b110 #
#845000
b111 #
#850000
1!
b0 #
#855000
0!
b10100 "
#860000
b1 #
#865000
1!
b10 #
#870000
0!
b11 #
#875000
1!
b100 #
#880000
0!
b101 #
#885000
b110 #
#890000
b111 #
#895000
b0 #
#900000
1!
b10101 "
#905000
0!
b1 #
#910000
1!
b10 #
#915000
0!
b11 #
#920000
1!
b100 #
#925000
0!
b101 #
#930000
b110 #
#935000
b111 #
#940000
1!
b0 #
#945000
0!
b10110 "
#950000
1!
b1 #
#955000
1!
b10 #
#960000
0!
b11 #
#965000
1!
b100 #
#970000
0!
b101 #
#975000
b110 #
#980000
b111 #
#985000
0!
b0 #
#990000
1!
b10111 "
#995000
b1 #
#1000000
1!
b10 #
#1005000
0!
b11 #
#1010000
1!
b100 #
#1015000
0!
b101 #
#1020000
b110 #
#1025000
b111 #
#1030000
1!
b0 #
#1035000
0!
b11000 "
#1040000
b1 #
#1045000
0!
b10 #
#1050000
1!
b11 #
#1055000
1!
b100 #
#1060000
0!
b101 #
#1065000
b110 #
#1070000
b111 #
#1075000
0!
b0 #
#1080000
1!
b11001 "
#1085000
0!
b1 #
#1090000
0!
b10 #
#1095000
1!
b11 #
#1100000
1!
b100 #
#1105000
0!
b101 #
#1110000
b110 #
#1115000
b111 #
#1120000
1!
b0 #
#1125000
0!
b11010 "
#1130000
1!
b1 #
#1135000
0!
b10 #
#1140000
1!
b11 #
#1145000
1!
b100 #
#1150000
0!
b101 #
#1155000
b110 #
#1160000
b111 #
#1165000
0!
b0 #
#1170000
1!
b11011 "
#1175000
b1 #
#1180000
0!
b10 #
#1185000
1!
b11 #
#1190000
1!
b100 #
#1195000
0!
b101 #
#1200000
b110 #
#1205000
b111 #
#1210000
1!
b0 #
#1215000
0!
b11100 "
#1220000
b1 #
#1225000
1!
b10 #
#1230000
b11 #
#1235000
1!
b100 #
#1240000
0!
b101 #
#1245000
b110 #
#1250000
b111 #
#1255000
0!
b0 #
#1260000
1!
b11101 "
#1265000
0!
b1 #
#1270000
1!
b10 #
#1275000
b11 #
#1280000
1!
b100 #
#1285000
0!
b101 #
#1290000
b110 #
#1295000
b111 #
#1300000
1!
b0 #
#1305000
0!
b11110 "
#1310000
1!
b1 #
#1315000
b10 #
#1320000
b11 #
#1325000
1!
b100 #
#1330000
0!
b101 #
#1335000
b110 #
#1340000
b111 #
#1345000
0!
b0 #
#1350000
1!
b11111 "
#1355000
b1 #
#1360000
b10 #
#1365000
b11 #
#1370000
1!
b100 #
#1375000
0!
b101 #
#1380000
b110 #
#1385000
b111 #
#1390000
1!
b0 #
#1395000
0!
b100000 "
#1400000
b1 #
#1405000
b10 #
#1410000
b11 #
#1415000
0!
b100 #
#1420000
1!
b101 #
#1425000
0!
b110 #
#1430000
b111 #
#1435000
b0 #
#1440000
1!
b100001 "
#1445000
0!
b1 #
#1450000
b10 #
#1455000
b11 #
#1460000
0!
b100 #
#1465000
1!
b101 #
#1470000
0!
b110 #
#1475000
b111 #
#1480000
1!
b0 #
#1485000
0!
b100010 "
#1490000
1!
b1 #
#1495000
0!
b10 #
#1500000
b11 #
#1505000
0!
b100 #
#1510000
1!
b101 #
#1515000
0!
b110 #
#1520000
b111 #
#1525000
0!
b0 #
#1530000
1!
b100011 "
#1535000
b1 #
#1540000
0!
b10 #
#1545000
b11 #
#1550000
0!
b100 #
#1555000
1!
b101 #
#1560000
0!
b110 #
#1565000
b111 #
#1570000
1!
b0 #
#1575000
0!
b100100 "
#1580000
b1 #
#1585000
1!
b10 #
#1590000
0!
b11 #
#1595000
0!
b100 #
#1600000
1!
b101 #
#1605000
0!
b110 #
#1610000
b111 #
#1615000
b0 #
#1620000
1!
b100101 "
#1625000
0!
b1 #
#1630000
1!
b10 #
#1635000
0!
b11 #
#1640000
0!
b100 #
#1645000
1!
b101 #
#1650000
0!
b110 #
#1655000
b111 #
#1660000
1!
b0 #
#1665000
0!
b100110 "
#1670000
1!
b1 #
#1675000
1!
b10 #
#1680000
0!
b11 #
#1685000
0!
b100 #
#1690000
1!
b101 #
#1695000
0!
b110 #
#1700000
b111 #
#1705000
0!
b0 #
#1710000
1!
b100111 "
#1715000
b1 #
#1720000
1!
b10 #
#1725000
0!
b11 #
#1730000
0!
b100 #
#1735000
1!
b101 #
#1740000
0!
b110 #
#1745000
b111 #
#1750000
1!
b0 #
#1755000
0!
b101000 "
#1760000
b1 #
#1765000
0!
b10 #
#1770000
1!
b11 #
#1775000
0!
b100 #
#1780000
1!
b101 #
#1785000
0!
b110 #
#1790000
b111 #
#1795000
0!
b0 #
#1800000
1!
b101001 "
#1805000
0!
b1 #
#1810000
0!
b10 #
#1815000
1!
b11 #
#1820000
0!
b100 #
#1825000
1!
b101 #
#1830000
0!
b110 #
#1835000
b111 #
#1840000
1!
b0 #
#1845000
0!
b101010 "
#1850000
1!
b1 #
#1855000
0!
b10 #
#1860000
1!
b11 #
#1865000
0!
b100 #
#1870000
1!
b101 #
#1875000
0!
b110 #
#1880000
b111 #
#1885000
0!
b0 #
#1890000
1!
b101011 "
#1895000
b1 #
#1900000
0!
b10 #
#1905000
1!
b11 #
#1910000
0!
b100 #
#1915000
1!
b101 #
#1920000
0!
b110 #
#1925000
b111 #
#1930000
1!
b0 #
#1935000
0!
b101100 "
#1940000
b1 #
#1945000
1!
b10 #
#1950000
b11 #
#1955000
0!
b100 #
#1960000
1!
b101 #
#1965000
0!
b110 #
#1970000
b111 #
#1975000
0!
b0 #
#1980000
1!
b101101 "
#1985000
0!
b1 #
#1990000
1!
b10 #
#1995000
b11 #
#2000000
0!
b100 #
#2005000
1!
b101 #
#2010000
0!
b110 #
#2015000
b111 #
#2020000
1!
b0 #
#2025000
0!
b101110 "
#2030000
1!
b1 #
#2035000
b10 #
#2040000
b11 #
#2045000
0!
b100 #
#2050000
1!
b101 #
#2055000
0!
b110 #
#2060000
b111 #
#2065000
0!
b0 #
#2070000
1!
b101111 "
#2075000
b1 #
#2080000
b10 #
#2085000
b11 #
#2090000
0!
b100 #
#2095000
1!
b101 #
#2100000
0!
b110 #
#2105000
b111 #
#2110000
1!
b0 #
#2115000
0!
b110000 "
#2120000
b1 #
#2125000
b10 #
#2130000
b11 #
#2135000
1!
b100 #
#2140000
b101 #
#2145000
0!
b110 #
#2150000
b111 #
#2155000
b0 #
#2160000
1!
b110001 "
#2165000
0!
b1 #
#2170000
b10 #
#2175000
b11 #
#2180000
1!
b100 #
#2185000
b101 #
#2190000
0!
b110 #
#2195000
b111 #
#2200000
1!
b0 #
#2205000
0!
b110010 "
#2210000
1!
b1 #
#2215000
0!
b10 #
#2220000
b11 #
#2225000
1!
b100 #
#2230000
b101 #
#2235000
0!
b110 #
#2240000
b111 #
#2245000
0!
b0 #
#2250000
1!
b110011 "
#2255000
b1 #
#2260000
0!
b10 #
#2265000
b11 #
#2270000
1!
b100 #
#2275000
b101 #
#2280000
0!
b110 #
#2285000
b111 #
#2290000
1!
b0 #
#2295000
0!
b110100 "
#2300000
b1 #
#2305000
1!
b10 #
#2310000
0!
b11 #
#2315000
1!
b100 #
#2320000
b101 #
#2325000
0!
b110 #
#2330000
b111 #
#2335000
b0 #
#2340000
1!
b110101 "
#2345000
0!
b1 #
#2350000
1!
b10 #
#2355000
0!
b11 #
#2360000
1!
b100 #
#2365000
b101 #
#2370000
0!
b110 #
#2375000
b111 #
#2380000
1!
b0 #
#2385000
0!
b110110 "
#2390000
1!
b1 #
#2395000
1!
b10 #
#2400000
0!
b11 #
#2405000
1!
b100 #
#2410000
b101 #
#2415000
0!
b110 #
#2420000
b111 #
#2425000
0!
b0 #
#2430000
1!
b110111 "
#2435000
b1 #
#2440000
1!
b10 #
#2445000
0!
b11 #
#2450000
1!
b100 #
#2455000
b101 #
#2460000
0!
b110 #
#2465000
b111 #
#2470000
1!
b0 #
#2475000
0!
b111000 "
#2480000
b1 #
#2485000
0!
b10 #
#2490000
1!
b11 #
#2495000
1!
b100 #
#2500000
b101 #
#2505000
0!
b110 #
#2510000
b111 #
#2515000
0!
b0 #
#2520000
1!
b111001 "
#2525000
0!
b1 #
#2530000
0!
b10 #
#2535000
1!
b11 #
#2540000
1!
b100 #
#2545000
b101 #
#2550000
0!
b110 #
#2555000
b111 #
#2560000
1!
b0 #
#2565000
0!
b111010 "
#2570000
1!
b1 #
#2575000
0!
b10 #
#2580000
1!
b11 #
#2585000
1!
b100 #
#2590000
b101 #
#2595000
0!
b110 #
#2600000
b111 #
#2605000
0!
b0 #
#2610000
1!
b111011 "
#2615000
b1 #
#2620000
0!
b10 #
#2625000
1!
b11 #
#2630000
1!
b100 #
#2635000
b101 #
#2640000
0!
b110 #
#2645000
b111 #
#2650000
1!
b0 #
#2655000
0!
b111100 "
#2660000
b1 #
#2665000
1!
b10 #
#2670000
b11 #
#2675000
1!
b100 #
#2680000
b101 #
#2685000
0!
b110 #
#2690000
b111 #
#2695000
0!
b0 #
#2700000
1!
b111101 "
#2705000
0!
b1 #
#2710000
1!
b10 #
#2715000
b11 #
#2720000
1!
b100 #
#2725000
b101 #
#2730000
0!
b110 #
#2735000
b111 #
#2740000
1!
b0 #
#2745000
0!
b111110 "
#2750000
1!
b1 #
#2755000
b10 #
#2760000
b11 #
#2765000
1!
b100 #
#2770000
b101 #
#2775000
0!
b110 #
#2780000
b111 #
#2785000
0!
b0 #
#2790000
1!
b111111 "
#2795000
b1 #
#2800000
b10 #
#2805000
b11 #
#2810000
1!
b100 #
#2815000
b101 #
#2820000
0!
b110 #
#2825000
b111 #
#2830000
1!
b0 #
#2835000
0!
b1000000 "
#2840000
b1 #
#2845000
b10 #
#2850000
b11 #
#2855000
b100 #
#2860000
b101 #
#2865000
1!
b110 #
#2870000
0!
b111 #
#2875000
b0 #
#2880000
1!
b1000001 "
#2885000
0!
b1 #
#2890000
b10 #
#2895000
b11 #
#2900000
b100 #
#2905000
b101 #
#2910000
1!
b110 #
#2915000
0!
b111 #
#2920000
1!
b0 #
#2925000
0!
b1000010 "
#2930000
1!
b1 #
#2935000
0!
b10 #
#2940000
b11 #
#2945000
b100 #
#2950000
b101 #
#2955000
1!
b110 #
#2960000
0!
b111 #
#2965000
0!
b0 #
#2970000
1!
b1000011 "
#2975000
b1 #
#2980000
0!
b10 #
#2985000
b11 #
#2990000
b100 #
#2995000
b101 #
#3000000
1!
b110 #
#3005000
0!
b111 #
#3010000
1!
b0 #
#3015000
0!
b1000100 "
#3020000
b1 #
#3025000
1!
b10 #
#3030000
0!
b11 #
#3035000
b100 #
#3040000
b101 #
#3045000
1!
b110 #
#3050000
0!
b111 #
#3055000
b0 #
#3060000
1!
b1000101 "
#3065000
0!
b1 #
#3070000
1!
b10 #
#3075000
0!
b11 #
#3080000
b100 #
#3085000
b101 #
#3090000
1!
b110 #
#3095000
0!
b111 #
#3100000
1!
b0 #
#3105000
0!
b1000110 "
#3110000
1!
b1 #
#3115000
1!
b10 #
#3120000
0!
b11 #
#3125000
b100 #
#3130000
b101 #
#3135000
1!
b110 #
#3140000
0!
b111 #
#3145000
0!
b0 #
#3150000
1!
b1000111 "
#3155000
b1 #
#3160000
1!
b10 #
#3165000
0!
b11 #
#3170000
b100 #
#3175000
b101 #
#3180000
1!
b110 #
#3185000
0!
b111 #
#3190000
1!
b0 #
#3195000
0!
b1001000 "
#3200000
b1 #
#3205000
0!
b10 #
#3210000
1!
b11 #
#3215000
0!
b100 #
#3220000
b101 #
#3225000
1!
b110 #
#3230000
0!
b111 #
#3235000
0!
b0 #
#3240000
1!
b1001001 "
#3245000
0!
b1 #
#3250000
0!
b10 #
#3255000
1!
b11 #
#3260000
0!
b100 #
#3265000
b101 #
#3270000
1!
b110 #
#3275000
0!
b111 #
#3280000
1!
b0 #
#3285000
0!
b1001010 "
#3290000
1!
b1 #
#3295000
0!
b10 #
#3300000
1!
b11 #
#3305000
0!
b100 #
#3310000
b101 #
#3315000
1!
b110 #
#3320000
0!
b111 #
#3325000
0!
b0 #
#3330000
1!
b1001011 "
#3335000
b1 #
#3340000
0!
b10 #
#3345000
1!
b11 #
#3350000
0!
b100 #
#3355000
b101 #
#3360000
1!
b110 #
#3365000
0!
b111 #
#3370000
1!
b0 #
#3375000
0!
b1001100 "
#3380000
b1 #
#3385000
1!
b10 #
#3390000
b11 #
#3395000
0!
b100 #
#3400000
b101 #
#3405000
1!
b110 #
#3410000
0!
b111 #
#3415000
0!
b0 #
#3420000
1!
b1001101 "
#3425000
0!
b1 #
#3430000
1!
b10 #
#3435000
b11 #
#3440000
0!
b100 #
#3445000
b101 #
#3450000
1!
b110 #
#3455000
0!
b111 #
#3460000
1!
b0 #
#3465000
0!
b1001110 "
#3470000
1!
b1 #
#3475000
b10 #
#3480000
b11 #
#3485000
0!
b100 #
#3490000
b101 #
#3495000
1!
b110 #
#3500000
0!
b111 #
#3505000
0!
b0 #
#3510000
1!
b1001111 "
#3515000
b1 #
#3520000
b10 #
#3525000
b11 #
#3530000
0!
b100 #
#3535000
b101 #
#3540000
1!
b110 #
#3545000
0!
b111 #
#3550000
1!
b0 #
#3555000
0!
b1010000 "
#3560000
b1 #
#3565000
b10 #
#3570000
b11 #
#3575000
1!
b100 #
#3580000
0!
b101 #
#3585000
1!
b110 #
#3590000
0!
b111 #
#3595000
b0 #
#3600000
1!
b1010001 "
#3605000
0!
b1 #
#3610000
b10 #
#3615000
b11 #
#3620000
1!
b100 #
#3625000
0!
b101 #
#3630000
1!
b110 #
#3635000
0!
b111 #
#3640000
1!
b0 #
#3645000
0!
b1010010 "
#3650000
1!
b1 #
#3655000
0!
b10 #
#3660000
b11 #
#3665000
1!
b100 #
#3670000
0!
b101 #
#3675000
1!
b110 #
#3680000
0!
b111 #
#3685000
0!
b0 #
#3690000
1!
b1010011 "
#3695000
b1 #
#3700000
0!
b10 #
#3705000
b11 #
#3710000
1!
b100 #
#3715000
0!
b101 #
#3720000
1!
b110 #
#3725000
0!
b111 #
#3730000
1!
b0 #
#3735000
0!
b1010100 "
#3740000
b1 #
#3745000
1!
b10 #
#3750000
0!
b11 #
#3755000
1!
b100 #
#3760000
0!
b101 #
#3765000
1!
b110 #
#3770000
0!
b111 #
#3775000
b0 #
#3780000
1!
b1010101 "
#3785000
0!
b1 #
#3790000
1!
b10 #
#3795000
0!
b11 #
#3800000
1!
b100 #
#3805000
0!
b101 #
#3810000
1!
b110 #
#3815000
0!
b111 #
#3820000
1!
b0 #
#3825000
0!
b1010110 "
#3830000
1!
b1 #
#3835000
1!
b10 #
#3840000
0!
b11 #
#3845000
1!
b100 #
#3850000
0!
b101 #
#3855000
1!
b110 #
#3860000
0!
b111 #
#3865000
0!
b0 #
#3870000
1!
b1010111 "
#3875000
b1 #
#3880000
1!
b10 #
#3885000
0!
b11 #
#3890000
1!
b100 #
#3895000
0!
b101 #
#3900000
1!
b110 #
#3905000
0!
b111 #
#3910000
1!
b0 #
#3915000
0!
b1011000 "
#3920000
b1 #
#3925000
0!
b10 #
#3930000
1!
b11 #
#3935000
1!
b100 #
#3940000
0!
b101 #
#3945000
1!
b110 #
#3950000
0!
b111 #
#3955000
0!
b0 #
#3960000
1!
b1011001 "
#3965000
0!
b1 #
#3970000
0!
b10 #
#3975000
1!
b11 #
#3980000
1!
b100 #
#3985000
0!
b101 #
#3990000
1!
b110 #
#3995000
0!
b111 #
#4000000
1!
b0 #
#4005000
0!
b1011010 "
#4010000
1!
b1 #
#4015000
0!
b10 #
#4020000
1!
b11 #
#4025000
1!
b100 #
#4030000
0!
b101 #
#4035000
1!
b110 #
#4040000
0!
b111 #
#4045000
0!
b0 #
#4050000
1!
b1011011 "
#4055000
b1 #
#4060000
0!
b10 #
#4065000
1!
b11 #
#4070000
1!
b100 #
#4075000
0!
b101 #
#4080000
1!
b110 #
#4085000
0!
b111 #
#4090000
1!
b0 #
#4095000
0!
b1011100 "
#4100000
b1 #
#4105000
1!
b10 #
#4110000
b11 #
#4115000
1!
b100 #
#4120000
0!
b101 #
#4125000
1!
b110 #
#4130000
0!
b111 #
#4135000
0!
b0 #
#4140000
1!
b1011101 "
#4145000
0!
b1 #
#4150000
1!
b10 #
#4155000
b11 #
#4160000
1!
b100 #
#4165000
0!
b101 #
#4170000
1!
b110 #
#4175000
0!
b111 #
#4180000
1!
b0 #
#4185000
0!
b1011110 "
#4190000
1!
b1 #
#4195000
b10 #
#4200000
b11 #
#4205000
1!
b100 #
#4210000
0!
b101 #
#4215000
1!
b110 #
#4220000
0!
b111 #
#4225000
0!
b0 #
#4230000
1!
b1011111 "
#4235000
b1 #
#4240000
b10 #
#4245000
b11 #
#4250000
1!
b100 #
#4255000
0!
b101 #
#4260000
1!
b110 #
#4265000
0!
b111 #
#4270000
1!
b0 #
#4275000
0!
b1100000 "
#4280000
b1 #
#4285000
b10 #
#4290000
b11 #
#4295000
0!
b100 #
#4300000
1!
b101 #
#4305000
1!
b110 #
#4310000
0!
b111 #
#4315000
b0 #
#4320000
1!
b1100001 "
#4325000
0!
b1 #
#4330000
b10 #
#4335000
b11 #
#4340000
0!
b100 #
#4345000
1!
b101 #
#4350000
1!
b110 #
#4355000
0!
b111 #
#4360000
1!
b0 #
#4365000
0!
b1100010 "
#4370000
1!
b1 #
#4375000
0!
b10 #
#4380000
b11 #
#4385000
0!
b100 #
#4390000
1!
b101 #
#4395000
1!
b110 #
#4400000
0!
b111 #
#4405000
0!
b0 #
#4410000
1!
b1100011 "
#4415000
b1 #
#4420000
0!
b10 #
#4425000
b11 #
#4430000
0!
b100 #
#4435000
1!
b101 #
#4440000
1!
b110 #
#4445000
0!
b111 #
#4450000
1!
b0 #
#4455000
0!
b1100100 "
#4460000
b1 #
#4465000
1!
b10 #
#4470000
0!
b11 #
#4475000
0!
b100 #
#4480000
1!
b101 #
#4485000
1!
b110 #
#4490000
0!
b111 #
#4495000
b0 #
#4500000
1!
b1100101 "
#4505000
0!
b1 #
#4510000
1!
b10 #
#4515000
0!
b11 #
#4520000
0!
b100 #
#4525000
1!
b101 #
#4530000
1!
b110 #
#4535000
0!
b111 #
#4540000
1!
b0 #
#4545000
0!
b1100110 "
#4550000
1!
b1 #
#4555000
1!
b10 #
#4560000
0!
b11 #
#4565000
0!
b100 #
#4570000
1!
b101 #
#4575000
1!
b110 #
#4580000
0!
b111 #
#4585000
0!
b0 #
#4590000
1!
b1100111 "
#4595000
b1 #
#4600000
1!
b10 #
#4605000
0!
b11 #
#4610000
0!
b100 #
#4615000
1!
b101 #
#4620000
1!
b110 #
#4625000
0!
b111 #
#4630000
1!
b0 #
#4635000
0!
b1101000 "
#4640000
b1 #
#4645000
0!
b10 #
#4650000
1!
b11 #
#4655000
0!
b100 #
#4660000
1!
b101 #
#4665000
1!
b110 #
#4670000
0!
b111 #
#4675000
0!
b0 #
#4680000
1!
b1101001 "
#4685000
0!
b1 #
#4690000
0!
b10 #
#4695000
1!
b11 #
#4700000
0!
b100 #
#4705000
1!
b101 #
#4710000
1!
b110 #
#4715000
0!
b111 #
#4720000
1!
b0 #
#4725000
0!
b1101010 "
#4730000
1!
b1 #
#4735000
0!
b10 #
#4740000
1!
b11 #
#4745000
0!
b100 #
#4750000
1!
b101 #
#4755000
1!
b110 #
#4760000
0!
b111 #
#4765000
0!
b0 #
#4770000
1!
b1101011 "
#4775000
b1 #
#4780000
0!
b10 #
#4785000
1!
b11 #
#4790000
0!
b100 #
#4795000
1!
b101 #
#4800000
1!
b110 #
#4805000
0!
b111 #
#4810000
1!
b0 #
#4815000
0!
b1101100 "
#4820000
b1 #
#4825000
1!
b10 #
#4830000
b11 #
#4835000
0!
b100 #
#4840000
1!
b101 #
#4845000
1!
b110 #
#4850000
0!
b111 #
#4855000
0!
b0 #
#4860000
1!
b1101101 "
#4865000
0!
b1 #
#4870000
1!
b10 #
#4875000
b11 #
#4880000
0!
b100 #
#4885000
1!
b101 #
#4890000
1!
b110 #
#4895000
0!
b111 #
#4900000
1!
b0 #
#4905000
0!
b1101110 "
#4910000
1!
b1 #
#4915000
b10 #
#4920000
b11 #
#4925000
0!
b100 #
#4930000
1!
b101 #
#4935000
1!
b110 #
#4940000
0!
b111 #
#4945000
0!
b0 #
#4950000
1!
b1101111 "
#4955000
b1 #
#4960000
b10 #
#4965000
b11 #
#4970000
0!
b100 #
#4975000
1!
b101 #
#4980000
1!
b110 #
#4985000
0!
b111 #
#4990000
1!
b0 #
#4995000
0!
b1110000 "
#5000000
b1 #
#5005000
b10 #
#5010000
b11 #
#5015000
1!
b100 #
#5020000
b101 #
#5025000
1!
b110 #
#5030000
0!
b111 #
#5035000
b0 #
#5040000
1!
b1110001 "
#5045000
0!
b1 #
#5050000
b10 #
#5055000
b11 #
#5060000
1!
b100 #
#5065000
b101 #
#5070000
1!
b110 #
#5075000
0!
b111 #
#5080000
1!
b0 #
#5085000
0!
b1110010 "
#5090000
1!
b1 #
#5095000
0!
b10 #
#5100000
b11 #
#5105000
1!
b100 #
#5110000
b101 #
#5115000
1!
b110 #
#5120000
0!
b111 #
#5125000
0!
b0 #
#5130000
1!
b1110011 "
#5135000
b1 #
#5140000
0!
b10 #
#5145000
b11 #
#5150000
1!
b100 #
#5155000
b101 #
#5160000
1!
b110 #
#5165000
0!
b111 #
#5170000
1!
b0 #
#5175000
0!
b1110100 "
#5180000
b1 #
#5185000
1!
b10 #
#5190000
0!
b11 #
#5195000
1!
b100 #
#5200000
b101 #
#5205000
1!
b110 #
#5210000
0!
b111 #
#5215000
b0 #
#5220000
1!
b1110101 "
#5225000
0!
b1 #
#5230000
1!
b10 #
#5235000
0!
b11 #
#5240000
1!
b100 #
#5245000
b101 #
#5250000
1!
b110 #
#5255000
0!
b111 #
#5260000
1!
b0 #
#5265000
0!
b1110110 "
#5270000
1!
b1 #
#5275000
1!
b10 #
#5280000
0!
b11 #
#5285000
1!
b100 #
#5290000
b101 #
#5295000
1!
b110 #
#5300000
0!
b111 #
#5305000
0!
b0 #
#5310000
1!
b1110111 "
#5315000
b1 #
#5320000
1!
b10 #
#5325000
0!
b11 #
#5330000
1!
b100 #
#5335000
b101 #
#5340000
1!
b110 #
#5345000
0!
b111 #
#5350000
1!
b0 #
#5355000
0!
b1111000 "
#5360000
b1 #
#5365000
0!
b10 #
#5370000
1!
b11 #
#5375000
1!
b100 #
#5380000
b101 #
#5385000
1!
b110 #
#5390000
0!
b111 #
#5395000
0!
b0 #
#5400000
1!
b1111001 "
#5405000
0!
b1 #
#5410000
0!
b10 #
#5415000
1!
b11 #
#5420000
1!
b100 #
#5425000
b101 #
#5430000
1!
b110 #
#5435000
0!
b111 #
#5440000
1!
b0 #
#5445000
0!
b1111010 "
#5450000
1!
b1 #
#5455000
0!
b10 #
#5460000
1!
b11 #
#5465000
1!
b100 #
#5470000
b101 #
#5475000
1!
b110 #
#5480000
0!
b111 #
#5485000
0!
b0 #
#5490000
1!
b1111011 "
#5495000
b1 #
#5500000
0!
b10 #
#5505000
1!
b11 #
#5510000
1!
b100 #
#5515000
b101 #
#5520000
1!
b110 #
#5525000
0!
b111 #
#5530000
1!
b0 #
#5535000
0!
b1111100 "
#5540000
b1 #
#5545000
1!
b10 #
#5550000
b11 #
#5555000
1!
b100 #
#5560000
b101 #
#5565000
1!
b110 #
#5570000
0!
b111 #
#5575000
0!
b0 #
#5580000
1!
b1111101 "
#5585000
0!
b1 #
#5590000
1!
b10 #
#5595000
b11 #
#5600000
1!
b100 #
#5605000
b101 #
#5610000
1!
b110 #
#5615000
0!
b111 #
#5620000
1!
b0 #
#5625000
0!
b1111110 "
#5630000
1!
b1 #
#5635000
b10 #
#5640000
b11 #
#5645000
1!
b100 #
#5650000
b101 #
#5655000
1!
b110 #
#5660000
0!
b111 #
#5665000
0!
b0 #
#5670000
1!
b1111111 "
#5675000
b1 #
#5680000
b10 #
#5685000
b11 #
#5690000
1!
b100 #
#5695000
b101 #
#5700000
1!
b110 #
#5705000
0!
b111 #
#5710000
1!
b0 #
#5715000
0!
b10000000 "
#5720000
b1 #
#5725000
b10 #
#5730000
b11 #
#5735000
0!
b100 #
#5740000
b101 #
#5745000
0!
b110 #
#5750000
1!
b111 #
