4th_day/mux2x1.v
module mux2x1 (
    y,a,b,sel
);

input a,b,sel;
output y;

assign y = sel?b:a;
   
endmodule

4th_day/mux4x1/mux4x1.v
`include "/share_folder/verilog/new/100_days_of_RTL/4th_day/mux2x1.v"
//mux3x1 using 2x1 mux

module mux4x1 (
    input [3:0]i,
    input [1:0]sel,
    output y
    
);

wire [1:0]w;

mux2x1 m1 (.a(i[0]),.b(i[1]),.sel(sel[0]),.y(w[0]));
mux2x1 m2 (.a(i[2]),.b(i[3]),.sel(sel[0]),.y(w[1]));

mux2x1 m3 (.a(w[0]),.b(w[1]),.sel(sel[1]),.y(y));
    
endmodule

4th_day/mux8x1/mux8x1.v
`include "/share_folder/verilog/new/100_days_of_RTL/4th_day/mux4x1/mux4x1.v"
// making 8x1 mux by using 2 4x1 and 1 2x1 muxes


module mux8x1 (
    I,SEL,Y
);

input [7:0]I;
input [2:0]SEL;
output Y;
wire [1:0]W;


mux4x1 M1 (.i(I[3:0]),.sel(SEL[1:0]),.y(W[0]));
mux4x1 M2 (.i(I[7:4]),.sel(SEL[1:0]),.y(W[1]));


mux2x1 M3 (.a(W[0]),.b(W[1]),.sel(SEL[2]),.y(Y) );


  
endmodule

4th_day/mux8x1/mux8x1_tb.v
`timescale 1ns/1ps
`include "mux8x1.v"

module mux8x1_tb();

reg [7:0]I;
reg [2:0]SEL;
wire Y;

mux8x1 dut(I,SEL,Y);
initial begin
    $dumpfile ("mux8x1.vcd");
    $dumpvars(1);
    $monitor("I=%b\tSEL=%b\tY=%b\t",I,SEL,Y);
    I= 8'd1; SEL=3'b000;
    #5;
    repeat (8)begin
            repeat (8) begin
                #5 SEL = SEL+1;
            end
            SEL =3'b000;
            #5 I = I*2;
        
    end
    $finish;
end


endmodule

4th_day/mux8x1/mux8x1.vcd
$date
	Fri Apr  4 16:29:30 2025
$end
$version
	Icarus Verilog
$end
$timescale
	1ps
$end
$scope module mux8x1_tb $end
$var wire 1 ! Y $end
$var reg 8 " I [7:0] $end
$var reg 3 # SEL [2:0] $end
$upscope $end
$enddefinitions $end
$comment Show the parameter values. $end
$dumpall
$end
#0
$dumpvars
b0 #
b1 "
1!
$end
#10000
0!
b1 #
#15000
b10 #
#20000
b11 #
#25000
b100 #
#30000
b101 #
#35000
b110 #
#40000
b111 #
#45000
1!
b0 #
#50000
0!
b10 "
#55000
1!
b1 #
#60000
0!
b10 #
#65000
b11 #
#70000
b100 #
#75000
b101 #
#80000
b110 #
#85000
b111 #
#90000
0!
b0 #
#95000
b100 "
#100000
b1 #
#105000
1!
b10 #
#110000
0!
b11 #
#115000
b100 #
#120000
b101 #
#125000
b110 #
#130000
b111 #
#135000
b0 #
#140000
b1000 "
#145000
b1 #
#150000
0!
b10 #
#155000
1!
b11 #
#160000
0!
b100 #
#165000
b101 #
#170000
b110 #
#175000
b111 #
#180000
0!
b0 #
#185000
b10000 "
#190000
b1 #
#195000
b10 #
#200000
b11 #
#205000
1!
b100 #
#210000
0!
b101 #
#215000
b110 #
#220000
b111 #
#225000
b0 #
#230000
b100000 "
#235000
b1 #
#240000
b10 #
#245000
b11 #
#250000
0!
b100 #
#255000
1!
b101 #
#260000
0!
b110 #
#265000
b111 #
#270000
b0 #
#275000
b1000000 "
#280000
b1 #
#285000
b10 #
#290000
b11 #
#295000
b100 #
#300000
b101 #
#305000
1!
b110 #
#310000
0!
b111 #
#315000
b0 #
#320000
b10000000 "
#325000
b1 #
#330000
b10 #
#335000
b11 #
#340000
0!
b100 #
#345000
b101 #
#350000
0!
b110 #
#355000
1!
b111 #
#360000
0!
b0 #
#365000
b0 "
