4th_day/mux2x1.v
module mux2x1 (
    y,a,b,sel
);

input a,b,sel;
output y;

assign y = sel?b:a;
   
endmodule

4th_day/mux2x1_tb.v
`timescale 1ns/1ps
`include "mux2x1.v"

module mux2x1_tb();

reg a,b,sel;
wire y;

mux2x1 dut(.y(y),.a(a),.b(b),.sel(sel));

initial begin
    $dumpfile ("mux2x1.vcd");
    $dumpvars(1);
    $monitor("a=%b\tb=%b\tsel=%b\ty=%b\t",a,b,sel,y);
    a=1;b=1;sel=0;
    repeat (2)begin
        #5 a=~a;
        repeat (2)begin
            #5 b=~b;
            repeat (2) begin
                #5 sel = ~sel;
            end
        end
    end
    
    $finish;
end




endmodule

4th_day/mux2x1.vcd
$date
	Thu Mar 27 13:37:14 2025
$end
$version
	Icarus Verilog
$end
$timescale
	1ps
$end
$scope module mux2x1_tb $end
$var wire 1 ! y $end
$var reg 1 " a $end
$var reg 1 # b $end
$var reg 1 $ sel $end
$upscope $end
$enddefinitions $end
$comment Show the parameter values. $end
$dumpall
$end
#0
$dumpvars
0$
1#
1"
1!
$end
#5000
0!
0"
#10000
0#
#15000
1$
#20000
0$
#25000
1#
#30000
1!
1$
#35000
0!
0$
#40000
1!
1"
#45000
0#
#50000
0!
1$
#55000
1!
0$
#60000
1#
#65000
1$
#70000
0$
