2nd_day/decoder.v
module  decoder (
    input [2:0]in,
    output reg [7:0] out
);

always @(*) begin
    case (in)
        3'b000 :out = 8'b00000001; 
        3'b001 :out = 8'b00000010; 
        3'b010 :out = 8'b00000100; 
        3'b011 :out = 8'b00001000; 
        3'b100 :out = 8'b00010000; 
        3'b101 :out = 8'b00100000; 
        3'b110 :out = 8'b01000000; 
        3'b111 :out = 8'b10000000; 
        default: begin
            out = 8'bxxxxxxxx;
        end
    endcase
end
    
endmodule

2nd_day/decoder_tb.v
`timescale 1ns/1ps
`include "decoder.v"

module decoder_tb ();

reg [2:0] in;
wire [7:0]out;

decoder dut (.in(in), .out(out));

initial begin
    $dumpfile("decoder.vcd");
    $dumpvars(1);
    $display ("Input      |   Output\n");
    
    $monitor("%b        |   %b",in,out);
    in = 0;
    #5;
    repeat (8) begin
        #5 in =in +1;
    end
end


endmodule

2nd_day/decoder.vcd
$date
	Wed Mar 26 01:12:38 2025
$end
$version
	Icarus Verilog
$end
$timescale
	1ps
$end
$scope module decoder_tb $end
$var wire 8 ! out [7:0] $end
$var reg 3 " in [2:0] $end
$upscope $end
$enddefinitions $end
$comment Show the parameter values. $end
$dumpall
$end
#0
$dumpvars
b0 "
b1 !
$end
#10000
b10 !
b1 "
#15000
b100 !
b10 "
#20000
b1000 !
b11 "
#25000
b10000 !
b100 "
#30000
b100000 !
b101 "
#35000
b1000000 !
b110 "
#40000
b10000000 !
b111 "
#45000
b1 !
b0 "
